{"includeInstallScript":[{"filePath":"/home2/wenbo/Documents/NPMAnalysis/Dataset/unzip_benign/vigemclient/1.5.2/package/package.json","content":"node-gyp rebuild"}],"includeIP":[],"useBase64Conversion":[],"useBase64ConversionInScript":[],"includeDomain":[],"includeDomainInScript":[],"includeByteString":[],"useBuffer":[],"useEval":[],"useProcess":[],"useProcessInScript":[],"useFileSystem":[],"useFileSystemInScript":[],"useNetwork":[],"useNetworkInScript":[],"useProcessEnv":[],"useProcessEnvInScript":[],"useEncryptAndEncode":[],"useOperatingSystem":[],"includeObfuscatedCode":[],"includeSensitiveFiles":[]}