{"includeInstallScript":[],"includeIP":[],"useBase64Conversion":[],"useBase64ConversionInScript":[],"includeDomain":[],"includeDomainInScript":[],"includeByteString":[],"useBuffer":[],"useEval":[{"filePath":"/home2/wenbo/Documents/NPMAnalysis/Dataset/unzip_benign/obj-creator/1.0.5/package/build/obj-creator.js","content":{"start":{"line":202,"column":34,"index":5126},"end":{"line":202,"column":38,"index":5130},"identifierName":"eval"}},{"filePath":"/home2/wenbo/Documents/NPMAnalysis/Dataset/unzip_benign/obj-creator/1.0.5/package/build/obj-creator.js","content":{"start":{"line":208,"column":4,"index":5277},"end":{"line":208,"column":8,"index":5281},"identifierName":"eval"}},{"filePath":"/home2/wenbo/Documents/NPMAnalysis/Dataset/unzip_benign/obj-creator/1.0.5/package/build/obj-creator.min.js","content":{"start":{"line":1,"column":861,"index":861},"end":{"line":1,"column":865,"index":865},"identifierName":"eval"}},{"filePath":"/home2/wenbo/Documents/NPMAnalysis/Dataset/unzip_benign/obj-creator/1.0.5/package/build/obj-creator.min.js","content":{"start":{"line":1,"column":980,"index":980},"end":{"line":1,"column":984,"index":984},"identifierName":"eval"}},{"filePath":"/home2/wenbo/Documents/NPMAnalysis/Dataset/unzip_benign/obj-creator/1.0.5/package/src/validator.js","content":{"start":{"line":198,"column":34,"index":5005},"end":{"line":198,"column":38,"index":5009},"identifierName":"eval"}},{"filePath":"/home2/wenbo/Documents/NPMAnalysis/Dataset/unzip_benign/obj-creator/1.0.5/package/src/validator.js","content":{"start":{"line":204,"column":4,"index":5154},"end":{"line":204,"column":8,"index":5158},"identifierName":"eval"}}],"useProcess":[],"useProcessInScript":[],"useFileSystem":[],"useFileSystemInScript":[],"useNetwork":[],"useNetworkInScript":[],"useProcessEnv":[],"useProcessEnvInScript":[],"useEncryptAndEncode":[],"useOperatingSystem":[],"includeObfuscatedCode":[],"includeSensitiveFiles":[]}