{
  "metadata": {
    "analysis_type": "joint_detection",
    "primary_tool": "packj_trace",
    "secondary_tool": "sap_XGB",
    "description": "False negatives remaining after joint detection with packj_trace and sap_XGB"
  },
  "statistics": {
    "tool1_name": "packj_trace",
    "tool2_name": "sap_XGB",
    "tool1_false_negatives": 83,
    "tool2_false_negatives": 1163,
    "joint_false_negatives": 83,
    "improvement_over_tool1": 0,
    "improvement_over_tool2": 1080,
    "improvement_rate_tool1_percent": 0.0,
    "improvement_rate_tool2_percent": 92.86,
    "packages_detected_by_tool2_only": 0,
    "packages_detected_by_tool1_only": 1080
  },
  "remaining_false_negatives": {
    "@fixedwidthtable##fixedwidthtable/0.0.1": {
      "prediction": "benign",
      "actual": "malware",
      "tool1_prediction": "benign",
      "tool2_prediction": "benign",
      "tools": "packj_trace+sap_XGB"
    },
    "@fixedwidthtable##fixedwidthtable/0.0.3": {
      "prediction": "benign",
      "actual": "malware",
      "tool1_prediction": "benign",
      "tool2_prediction": "benign",
      "tools": "packj_trace+sap_XGB"
    },
    "@fixedwidthtable##fixedwidthtable/0.0.2": {
      "prediction": "benign",
      "actual": "malware",
      "tool1_prediction": "benign",
      "tool2_prediction": "benign",
      "tools": "packj_trace+sap_XGB"
    },
    "harthat-hash/1.3.3": {
      "prediction": "benign",
      "actual": "malware",
      "tool1_prediction": "benign",
      "tool2_prediction": "benign",
      "tools": "packj_trace+sap_XGB"
    },
    "color-self/1.4.0": {
      "prediction": "benign",
      "actual": "malware",
      "tool1_prediction": "benign",
      "tool2_prediction": "benign",
      "tools": "packj_trace+sap_XGB"
    },
    "pupetier/23.6.1": {
      "prediction": "benign",
      "actual": "malware",
      "tool1_prediction": "benign",
      "tool2_prediction": "benign",
      "tools": "packj_trace+sap_XGB"
    },
    "puppeteer-captre/1.1.1": {
      "prediction": "benign",
      "actual": "malware",
      "tool1_prediction": "benign",
      "tool2_prediction": "benign",
      "tools": "packj_trace+sap_XGB"
    },
    "purple-bitchs/1.4.0": {
      "prediction": "benign",
      "actual": "malware",
      "tool1_prediction": "benign",
      "tool2_prediction": "benign",
      "tools": "packj_trace+sap_XGB"
    },
    "styled-beautify-components/6.1.4": {
      "prediction": "benign",
      "actual": "malware",
      "tool1_prediction": "benign",
      "tool2_prediction": "benign",
      "tools": "packj_trace+sap_XGB"
    },
    "styled-beautify-components/6.1.3": {
      "prediction": "benign",
      "actual": "malware",
      "tool1_prediction": "benign",
      "tool2_prediction": "benign",
      "tools": "packj_trace+sap_XGB"
    },
    "styled-beautify-components/6.1.2": {
      "prediction": "benign",
      "actual": "malware",
      "tool1_prediction": "benign",
      "tool2_prediction": "benign",
      "tools": "packj_trace+sap_XGB"
    },
    "styled-beautify-components/6.1.6": {
      "prediction": "benign",
      "actual": "malware",
      "tool1_prediction": "benign",
      "tool2_prediction": "benign",
      "tools": "packj_trace+sap_XGB"
    },
    "styled-beautify-components/6.1.1": {
      "prediction": "benign",
      "actual": "malware",
      "tool1_prediction": "benign",
      "tool2_prediction": "benign",
      "tools": "packj_trace+sap_XGB"
    },
    "puppeteercaptur/1.1.1": {
      "prediction": "benign",
      "actual": "malware",
      "tool1_prediction": "benign",
      "tool2_prediction": "benign",
      "tools": "packj_trace+sap_XGB"
    },
    "eth-errors/4.0.3": {
      "prediction": "benign",
      "actual": "malware",
      "tool1_prediction": "benign",
      "tool2_prediction": "benign",
      "tools": "packj_trace+sap_XGB"
    },
    "color2.0/1.4.0": {
      "prediction": "benign",
      "actual": "malware",
      "tool1_prediction": "benign",
      "tool2_prediction": "benign",
      "tools": "packj_trace+sap_XGB"
    },
    "colors-personaly/1.4.0": {
      "prediction": "benign",
      "actual": "malware",
      "tool1_prediction": "benign",
      "tool2_prediction": "benign",
      "tools": "packj_trace+sap_XGB"
    },
    "passports-js/0.7.1": {
      "prediction": "benign",
      "actual": "malware",
      "tool1_prediction": "benign",
      "tool2_prediction": "benign",
      "tools": "packj_trace+sap_XGB"
    },
    "passports-js/0.7.0": {
      "prediction": "benign",
      "actual": "malware",
      "tool1_prediction": "benign",
      "tool2_prediction": "benign",
      "tools": "packj_trace+sap_XGB"
    },
    "color2.1/1.4.0": {
      "prediction": "benign",
      "actual": "malware",
      "tool1_prediction": "benign",
      "tool2_prediction": "benign",
      "tools": "packj_trace+sap_XGB"
    },
    "github-jquery-widgets/0.1.2": {
      "prediction": "benign",
      "actual": "malware",
      "tool1_prediction": "benign",
      "tool2_prediction": "benign",
      "tools": "packj_trace+sap_XGB"
    },
    "colors-support/1.5.3": {
      "prediction": "benign",
      "actual": "malware",
      "tool1_prediction": "benign",
      "tool2_prediction": "benign",
      "tools": "packj_trace+sap_XGB"
    },
    "@spgy##eslint-plugin-spgy-fe/rc.2": {
      "prediction": "benign",
      "actual": "malware",
      "tool1_prediction": "benign",
      "tool2_prediction": "benign",
      "tools": "packj_trace+sap_XGB"
    },
    "@spgy##eslint-plugin-spgy-fe/rc.0": {
      "prediction": "benign",
      "actual": "malware",
      "tool1_prediction": "benign",
      "tool2_prediction": "benign",
      "tools": "packj_trace+sap_XGB"
    },
    "@spgy##eslint-plugin-spgy-fe/rc.1": {
      "prediction": "benign",
      "actual": "malware",
      "tool1_prediction": "benign",
      "tool2_prediction": "benign",
      "tools": "packj_trace+sap_XGB"
    },
    "hardhat-cookie/3.8.9": {
      "prediction": "benign",
      "actual": "malware",
      "tool1_prediction": "benign",
      "tool2_prediction": "benign",
      "tools": "packj_trace+sap_XGB"
    },
    "divinity-color/1.4.0": {
      "prediction": "benign",
      "actual": "malware",
      "tool1_prediction": "benign",
      "tool2_prediction": "benign",
      "tools": "packj_trace+sap_XGB"
    },
    "colors-person/1.4.0": {
      "prediction": "benign",
      "actual": "malware",
      "tool1_prediction": "benign",
      "tool2_prediction": "benign",
      "tools": "packj_trace+sap_XGB"
    },
    "bigumner-js/9.1.2": {
      "prediction": "benign",
      "actual": "malware",
      "tool1_prediction": "benign",
      "tool2_prediction": "benign",
      "tools": "packj_trace+sap_XGB"
    },
    "ether-multcal/0.2.3": {
      "prediction": "benign",
      "actual": "malware",
      "tool1_prediction": "benign",
      "tool2_prediction": "benign",
      "tools": "packj_trace+sap_XGB"
    },
    "color-2.0/1.4.0": {
      "prediction": "benign",
      "actual": "malware",
      "tool1_prediction": "benign",
      "tool2_prediction": "benign",
      "tools": "packj_trace+sap_XGB"
    },
    "stream-of-end/1.4.4": {
      "prediction": "benign",
      "actual": "malware",
      "tool1_prediction": "benign",
      "tool2_prediction": "benign",
      "tools": "packj_trace+sap_XGB"
    },
    "ethers-multicaal/0.2.3": {
      "prediction": "benign",
      "actual": "malware",
      "tool1_prediction": "benign",
      "tool2_prediction": "benign",
      "tools": "packj_trace+sap_XGB"
    },
    "eth-rperrors/4.0.3": {
      "prediction": "benign",
      "actual": "malware",
      "tool1_prediction": "benign",
      "tool2_prediction": "benign",
      "tools": "packj_trace+sap_XGB"
    },
    "dom-seriaiizer/1.2.0": {
      "prediction": "benign",
      "actual": "malware",
      "tool1_prediction": "benign",
      "tool2_prediction": "benign",
      "tools": "packj_trace+sap_XGB"
    },
    "harthat-chain/4.1.2": {
      "prediction": "benign",
      "actual": "malware",
      "tool1_prediction": "benign",
      "tool2_prediction": "benign",
      "tools": "packj_trace+sap_XGB"
    },
    "harthat-chain/4.2.3": {
      "prediction": "benign",
      "actual": "malware",
      "tool1_prediction": "benign",
      "tool2_prediction": "benign",
      "tools": "packj_trace+sap_XGB"
    },
    "bs58lite/2.3.2": {
      "prediction": "benign",
      "actual": "malware",
      "tool1_prediction": "benign",
      "tool2_prediction": "benign",
      "tools": "packj_trace+sap_XGB"
    },
    "legacyreact-aws-s3-typescript/1.2.4": {
      "prediction": "benign",
      "actual": "malware",
      "tool1_prediction": "benign",
      "tool2_prediction": "benign",
      "tools": "packj_trace+sap_XGB"
    },
    "colorzinha/1.4.0": {
      "prediction": "benign",
      "actual": "malware",
      "tool1_prediction": "benign",
      "tool2_prediction": "benign",
      "tools": "packj_trace+sap_XGB"
    },
    "puppeteercluser/0.24.0": {
      "prediction": "benign",
      "actual": "malware",
      "tool1_prediction": "benign",
      "tool2_prediction": "benign",
      "tools": "packj_trace+sap_XGB"
    },
    "ethblk-tracker/8.1.0": {
      "prediction": "benign",
      "actual": "malware",
      "tool1_prediction": "benign",
      "tool2_prediction": "benign",
      "tools": "packj_trace+sap_XGB"
    },
    "react-dom-production-script/0.21.0": {
      "prediction": "benign",
      "actual": "malware",
      "tool1_prediction": "benign",
      "tool2_prediction": "benign",
      "tools": "packj_trace+sap_XGB"
    },
    "safebs58.js/2.3.2": {
      "prediction": "benign",
      "actual": "malware",
      "tool1_prediction": "benign",
      "tool2_prediction": "benign",
      "tools": "packj_trace+sap_XGB"
    },
    "pupeteer-capture/1.1.1": {
      "prediction": "benign",
      "actual": "malware",
      "tool1_prediction": "benign",
      "tool2_prediction": "benign",
      "tools": "packj_trace+sap_XGB"
    },
    "web3-core-subscription/6.1.6": {
      "prediction": "benign",
      "actual": "malware",
      "tool1_prediction": "benign",
      "tool2_prediction": "benign",
      "tools": "packj_trace+sap_XGB"
    },
    "angular-location-update/0.0.3": {
      "prediction": "benign",
      "actual": "malware",
      "tool1_prediction": "benign",
      "tool2_prediction": "benign",
      "tools": "packj_trace+sap_XGB"
    },
    "pupeteer-cluster/0.24.0": {
      "prediction": "benign",
      "actual": "malware",
      "tool1_prediction": "benign",
      "tool2_prediction": "benign",
      "tools": "packj_trace+sap_XGB"
    },
    "color2.0.0/1.4.0": {
      "prediction": "benign",
      "actual": "malware",
      "tool1_prediction": "benign",
      "tool2_prediction": "benign",
      "tools": "packj_trace+sap_XGB"
    },
    "ether-js-tx/2.1.2": {
      "prediction": "benign",
      "actual": "malware",
      "tool1_prediction": "benign",
      "tool2_prediction": "benign",
      "tools": "packj_trace+sap_XGB"
    },
    "ethblock-trackr/8.1.0": {
      "prediction": "benign",
      "actual": "malware",
      "tool1_prediction": "benign",
      "tool2_prediction": "benign",
      "tools": "packj_trace+sap_XGB"
    },
    "stars-color/1.4.0": {
      "prediction": "benign",
      "actual": "malware",
      "tool1_prediction": "benign",
      "tool2_prediction": "benign",
      "tools": "packj_trace+sap_XGB"
    },
    "stars-colors/1.4.0": {
      "prediction": "benign",
      "actual": "malware",
      "tool1_prediction": "benign",
      "tool2_prediction": "benign",
      "tools": "packj_trace+sap_XGB"
    },
    "color2.0.1/1.4.0": {
      "prediction": "benign",
      "actual": "malware",
      "tool1_prediction": "benign",
      "tool2_prediction": "benign",
      "tools": "packj_trace+sap_XGB"
    },
    "rc-calendar-jhorst/8.4.3": {
      "prediction": "benign",
      "actual": "malware",
      "tool1_prediction": "benign",
      "tool2_prediction": "benign",
      "tools": "packj_trace+sap_XGB"
    },
    "colors-help/1.4.0": {
      "prediction": "benign",
      "actual": "malware",
      "tool1_prediction": "benign",
      "tool2_prediction": "benign",
      "tools": "packj_trace+sap_XGB"
    },
    "apl-viewhost-web-2023.1.0/1": {
      "prediction": "benign",
      "actual": "malware",
      "tool1_prediction": "benign",
      "tool2_prediction": "benign",
      "tools": "packj_trace+sap_XGB"
    },
    "bignum.js/9.1.2": {
      "prediction": "benign",
      "actual": "malware",
      "tool1_prediction": "benign",
      "tool2_prediction": "benign",
      "tools": "packj_trace+sap_XGB"
    },
    "person-colors/1.4.0": {
      "prediction": "benign",
      "actual": "malware",
      "tool1_prediction": "benign",
      "tool2_prediction": "benign",
      "tools": "packj_trace+sap_XGB"
    },
    "pupeter/23.6.1": {
      "prediction": "benign",
      "actual": "malware",
      "tool1_prediction": "benign",
      "tool2_prediction": "benign",
      "tools": "packj_trace+sap_XGB"
    },
    "ethers-multcall/0.2.3": {
      "prediction": "benign",
      "actual": "malware",
      "tool1_prediction": "benign",
      "tool2_prediction": "benign",
      "tools": "packj_trace+sap_XGB"
    },
    "color2.3/1.4.0": {
      "prediction": "benign",
      "actual": "malware",
      "tool1_prediction": "benign",
      "tool2_prediction": "benign",
      "tools": "packj_trace+sap_XGB"
    },
    "harthat-cookie/2.5.9": {
      "prediction": "benign",
      "actual": "malware",
      "tool1_prediction": "benign",
      "tool2_prediction": "benign",
      "tools": "packj_trace+sap_XGB"
    },
    "react-datepicker-plus/2.4.2": {
      "prediction": "benign",
      "actual": "malware",
      "tool1_prediction": "benign",
      "tool2_prediction": "benign",
      "tools": "packj_trace+sap_XGB"
    },
    "color2.4/1.4.0": {
      "prediction": "benign",
      "actual": "malware",
      "tool1_prediction": "benign",
      "tool2_prediction": "benign",
      "tools": "packj_trace+sap_XGB"
    },
    "ethrereum-js-tx/2.1.2": {
      "prediction": "benign",
      "actual": "malware",
      "tool1_prediction": "benign",
      "tool2_prediction": "benign",
      "tools": "packj_trace+sap_XGB"
    },
    "eth-err/4.0.3": {
      "prediction": "benign",
      "actual": "malware",
      "tool1_prediction": "benign",
      "tool2_prediction": "benign",
      "tools": "packj_trace+sap_XGB"
    },
    "purple-bitch/1.4.0": {
      "prediction": "benign",
      "actual": "malware",
      "tool1_prediction": "benign",
      "tool2_prediction": "benign",
      "tools": "packj_trace+sap_XGB"
    },
    "divinity-colors/1.4.0": {
      "prediction": "benign",
      "actual": "malware",
      "tool1_prediction": "benign",
      "tool2_prediction": "benign",
      "tools": "packj_trace+sap_XGB"
    },
    "zalf22ausi8/23.6.1": {
      "prediction": "benign",
      "actual": "malware",
      "tool1_prediction": "benign",
      "tool2_prediction": "benign",
      "tools": "packj_trace+sap_XGB"
    },
    "leaflet-gpx/1.0.1": {
      "prediction": "benign",
      "actual": "malware",
      "tool1_prediction": "benign",
      "tool2_prediction": "benign",
      "tools": "packj_trace+sap_XGB"
    },
    "layout-utils.js/2.3.2": {
      "prediction": "benign",
      "actual": "malware",
      "tool1_prediction": "benign",
      "tool2_prediction": "benign",
      "tools": "packj_trace+sap_XGB"
    },
    "support-colors/1.4.0": {
      "prediction": "benign",
      "actual": "malware",
      "tool1_prediction": "benign",
      "tool2_prediction": "benign",
      "tools": "packj_trace+sap_XGB"
    },
    "nodejs-encrypt-agent/6.0.3": {
      "prediction": "benign",
      "actual": "malware",
      "tool1_prediction": "benign",
      "tool2_prediction": "benign",
      "tools": "packj_trace+sap_XGB"
    },
    "nodejs-encrypt-agent/6.0.4": {
      "prediction": "benign",
      "actual": "malware",
      "tool1_prediction": "benign",
      "tool2_prediction": "benign",
      "tools": "packj_trace+sap_XGB"
    },
    "nodejs-encrypt-agent/6.0.5": {
      "prediction": "benign",
      "actual": "malware",
      "tool1_prediction": "benign",
      "tool2_prediction": "benign",
      "tools": "packj_trace+sap_XGB"
    },
    "nodejs-encrypt-agent/6.0.2": {
      "prediction": "benign",
      "actual": "malware",
      "tool1_prediction": "benign",
      "tool2_prediction": "benign",
      "tools": "packj_trace+sap_XGB"
    },
    "eth-tracker/8.1.0": {
      "prediction": "benign",
      "actual": "malware",
      "tool1_prediction": "benign",
      "tool2_prediction": "benign",
      "tools": "packj_trace+sap_XGB"
    },
    "harthat-api/1.3.1": {
      "prediction": "benign",
      "actual": "malware",
      "tool1_prediction": "benign",
      "tool2_prediction": "benign",
      "tools": "packj_trace+sap_XGB"
    },
    "colors2.0/1.4.0": {
      "prediction": "benign",
      "actual": "malware",
      "tool1_prediction": "benign",
      "tool2_prediction": "benign",
      "tools": "packj_trace+sap_XGB"
    },
    "@virtualsearchtable##virtualsearchtable/0.1.0": {
      "prediction": "benign",
      "actual": "malware",
      "tool1_prediction": "benign",
      "tool2_prediction": "benign",
      "tools": "packj_trace+sap_XGB"
    },
    "@virtualsearchtable##virtualsearchtable/0.1.1": {
      "prediction": "benign",
      "actual": "malware",
      "tool1_prediction": "benign",
      "tool2_prediction": "benign",
      "tools": "packj_trace+sap_XGB"
    },
    "daun124wdsa8/23.6.1": {
      "prediction": "benign",
      "actual": "malware",
      "tool1_prediction": "benign",
      "tool2_prediction": "benign",
      "tools": "packj_trace+sap_XGB"
    }
  }
}