{"includeInstallScript":[],"includeIP":[],"useBase64Conversion":[],"useBase64ConversionInScript":[],"includeDomain":[{"filePath":"/home2/wenbo/Documents/NPMAnalysis/Dataset/unzip_benign/@jood##v-modal/0.11.3/package/dist/v-modal.umd.min.js","content":"github.com"},{"filePath":"/home2/wenbo/Documents/NPMAnalysis/Dataset/unzip_benign/@jood##v-modal/0.11.3/package/dist/v-modal.umd.min.js","content":"github.com"},{"filePath":"/home2/wenbo/Documents/NPMAnalysis/Dataset/unzip_benign/@jood##v-modal/0.11.3/package/dist/v-modal.umd.js","content":"github.com"},{"filePath":"/home2/wenbo/Documents/NPMAnalysis/Dataset/unzip_benign/@jood##v-modal/0.11.3/package/dist/v-modal.umd.js","content":"github.com"},{"filePath":"/home2/wenbo/Documents/NPMAnalysis/Dataset/unzip_benign/@jood##v-modal/0.11.3/package/dist/v-modal.common.js","content":"github.com"},{"filePath":"/home2/wenbo/Documents/NPMAnalysis/Dataset/unzip_benign/@jood##v-modal/0.11.3/package/dist/v-modal.common.js","content":"github.com"}],"includeDomainInScript":[],"includeByteString":[{"filePath":"/home2/wenbo/Documents/NPMAnalysis/Dataset/unzip_benign/@jood##v-modal/0.11.3/package/dist/v-modal.umd.min.js","content":"\\x3e"}],"useBuffer":[],"useEval":[],"useProcess":[],"useProcessInScript":[],"useFileSystem":[],"useFileSystemInScript":[],"useNetwork":[],"useNetworkInScript":[],"useProcessEnv":[],"useProcessEnvInScript":[],"useEncryptAndEncode":[],"useOperatingSystem":[],"includeObfuscatedCode":[],"includeSensitiveFiles":[]}