{
  "metadata": {
    "package_name": "axelhowe",
    "version": "ZPffIoH1",
    "snippet_count": 1
  },
  "snippets": [
    {
      "index": 0,
      "file": "package/index.js",
      "hash": "82c6ab186f10fb8a6a212fb7b4a978ac",
      "apis": {
        "network": [
          "fetch"
        ],
        "encoding": [
          "JSON.stringify"
        ]
      },
      "api_count": 2
    }
  ],
  "summary": {
    "total_apis": 2,
    "apis_by_category": {
      "network": [
        "fetch"
      ],
      "encoding": [
        "JSON.stringify"
      ]
    },
    "category_counts": {
      "network": 1,
      "encoding": 1
    }
  }
}