{
  "metadata": {
    "package_name": "iproduce",
    "version": "26.0.4",
    "snippet_count": 4
  },
  "snippets": [
    {
      "index": 0,
      "file": "package/main.js",
      "hash": "74dc1e4259c3ad78f6f7bb0e9bae8dc4",
      "apis": {
        "network": [
          "[module] https",
          "https.request",
          "request"
        ],
        "system_info": [
          "[module] os",
          "os.homedir",
          "os.hostname",
          "os.platform"
        ],
        "filesystem": [
          "[module] fs",
          "fs.read",
          "fs.readFile",
          "fs.readFileSync"
        ],
        "process_info": [
          "process.argv"
        ],
        "encoding": [
          "Buffer.from",
          "JSON.stringify"
        ]
      },
      "api_count": 14
    },
    {
      "index": 1,
      "file": "package/main.js",
      "hash": "74dc1e4259c3ad78f6f7bb0e9bae8dc4",
      "apis": {
        "network": [
          "[module] https",
          "https.request",
          "request"
        ],
        "system_info": [
          "[module] os",
          "os.homedir",
          "os.hostname",
          "os.platform"
        ],
        "filesystem": [
          "[module] fs",
          "fs.read",
          "fs.readFile",
          "fs.readFileSync"
        ],
        "process_info": [
          "process.argv"
        ],
        "encoding": [
          "Buffer.from",
          "JSON.stringify"
        ]
      },
      "api_count": 14
    },
    {
      "index": 2,
      "file": "package/main.js",
      "hash": "74dc1e4259c3ad78f6f7bb0e9bae8dc4",
      "apis": {
        "network": [
          "[module] https",
          "https.request",
          "request"
        ],
        "system_info": [
          "[module] os",
          "os.homedir",
          "os.hostname",
          "os.platform"
        ],
        "filesystem": [
          "[module] fs",
          "fs.read",
          "fs.readFile",
          "fs.readFileSync"
        ],
        "process_info": [
          "process.argv"
        ],
        "encoding": [
          "Buffer.from",
          "JSON.stringify"
        ]
      },
      "api_count": 14
    },
    {
      "index": 3,
      "file": "package/package.json",
      "hash": "de1a5be54fa90528fcdf93d7ee011551",
      "apis": {},
      "api_count": 0
    }
  ],
  "summary": {
    "total_apis": 14,
    "apis_by_category": {
      "network": [
        "[module] https",
        "https.request",
        "request"
      ],
      "system_info": [
        "[module] os",
        "os.homedir",
        "os.hostname",
        "os.platform"
      ],
      "filesystem": [
        "[module] fs",
        "fs.read",
        "fs.readFile",
        "fs.readFileSync"
      ],
      "process_info": [
        "process.argv"
      ],
      "encoding": [
        "Buffer.from",
        "JSON.stringify"
      ]
    },
    "category_counts": {
      "network": 3,
      "system_info": 4,
      "filesystem": 4,
      "process_info": 1,
      "encoding": 2
    }
  }
}