{"includeInstallScript":[],"includeIP":[],"useBase64Conversion":[],"useBase64ConversionInScript":[],"includeDomain":[],"includeDomainInScript":[],"includeByteString":[],"useBuffer":[],"useEval":[],"useProcess":[],"useProcessInScript":[],"useFileSystem":[{"filePath":"/home2/wenbo/Documents/NPMAnalysis/Dataset/unzip_benign/@redplc##node-red-rpi-ds18b20/2.0.4/package/nodes/lib/syslib.js","content":{"start":{"line":19,"column":11,"index":652},"end":{"line":19,"column":24,"index":665}}},{"filePath":"/home2/wenbo/Documents/NPMAnalysis/Dataset/unzip_benign/@redplc##node-red-rpi-ds18b20/2.0.4/package/setSensor/syslib.js","content":{"start":{"line":19,"column":11,"index":652},"end":{"line":19,"column":24,"index":665}}}],"useFileSystemInScript":[],"useNetwork":[],"useNetworkInScript":[],"useProcessEnv":[],"useProcessEnvInScript":[],"useEncryptAndEncode":[],"useOperatingSystem":[],"includeObfuscatedCode":[],"includeSensitiveFiles":[]}