{
  "metadata": {
    "package_name": "cosmos-wallet-js",
    "version": "1.0.3",
    "snippet_count": 1
  },
  "snippets": [
    {
      "index": 0,
      "file": "package/cosmos.js",
      "hash": "422d4b3f1069f3229b730b2a5ab0cb39",
      "apis": {
        "encoding": [
          "Buffer.toString",
          "JSON.stringify",
          "querystring.stringify"
        ],
        "network": [
          "[module] http",
          "[module] https",
          "http.request",
          "https.request",
          "request"
        ],
        "system_info": [
          "os.hostname"
        ],
        "filesystem": [
          "[module] path",
          "fs.write"
        ]
      },
      "api_count": 11
    }
  ],
  "summary": {
    "total_apis": 11,
    "apis_by_category": {
      "encoding": [
        "Buffer.toString",
        "JSON.stringify",
        "querystring.stringify"
      ],
      "network": [
        "[module] http",
        "[module] https",
        "http.request",
        "https.request",
        "request"
      ],
      "system_info": [
        "os.hostname"
      ],
      "filesystem": [
        "[module] path",
        "fs.write"
      ]
    },
    "category_counts": {
      "encoding": 3,
      "network": 5,
      "system_info": 1,
      "filesystem": 2
    }
  }
}