{"includeInstallScript":[],"includeIP":[],"useBase64Conversion":[],"useBase64ConversionInScript":[],"includeDomain":[],"includeDomainInScript":[],"includeByteString":[],"useBuffer":[],"useEval":[],"useProcess":[],"useProcessInScript":[],"useFileSystem":[{"filePath":"/home2/wenbo/Documents/NPMAnalysis/Dataset/unzip_benign/grunt-contrib-copy-faster/1.1.1/package/tasks/copy.js","content":{"start":{"line":13,"column":13,"index":299},"end":{"line":13,"column":28,"index":314}}},{"filePath":"/home2/wenbo/Documents/NPMAnalysis/Dataset/unzip_benign/grunt-contrib-copy-faster/1.1.1/package/tasks/copy.js","content":{"start":{"line":14,"column":11,"index":328},"end":{"line":14,"column":24,"index":341}}}],"useFileSystemInScript":[],"useNetwork":[],"useNetworkInScript":[],"useProcessEnv":[],"useProcessEnvInScript":[],"useEncryptAndEncode":[],"useOperatingSystem":[],"includeObfuscatedCode":[],"includeSensitiveFiles":[]}