{"includeInstallScript":[],"includeIP":[],"useBase64Conversion":[],"useBase64ConversionInScript":[],"includeDomain":[{"filePath":"/home2/wenbo/Documents/NPMAnalysis/Dataset/unzip_benign/jfractal/1.0.0/package/webpack.dev.js","content":"webpack.com"},{"filePath":"/home2/wenbo/Documents/NPMAnalysis/Dataset/unzip_benign/jfractal/1.0.0/package/webpack.prod.js","content":"webpack.com"},{"filePath":"/home2/wenbo/Documents/NPMAnalysis/Dataset/unzip_benign/jfractal/1.0.0/package/dist/jfractal.min.js","content":"3e72d29bc917a70dbf6f.work"}],"includeDomainInScript":[],"includeByteString":[],"useBuffer":[],"useEval":[],"useProcess":[],"useProcessInScript":[],"useFileSystem":[{"filePath":"/home2/wenbo/Documents/NPMAnalysis/Dataset/unzip_benign/jfractal/1.0.0/package/webpack.common.js","content":{"start":{"line":1,"column":13,"index":13},"end":{"line":1,"column":28,"index":28}}}],"useFileSystemInScript":[],"useNetwork":[],"useNetworkInScript":[],"useProcessEnv":[],"useProcessEnvInScript":[],"useEncryptAndEncode":[],"useOperatingSystem":[],"includeObfuscatedCode":[],"includeSensitiveFiles":[]}