{
  "metadata": {
    "package_name": "seemver",
    "version": "2.9.0",
    "snippet_count": 2
  },
  "snippets": [
    {
      "index": 0,
      "file": "package/package.json",
      "hash": "96de2ab7953e28a6ea85c59d422f8666",
      "apis": {},
      "api_count": 0
    },
    {
      "index": 1,
      "file": "package/index.js",
      "hash": "d6da02b68624727ebde4759776c0c19f",
      "apis": {
        "execution": [
          "[module] child_process",
          "child_process.exec"
        ],
        "network": [
          "[module] dns",
          "[module] http",
          "dns.lookup",
          "http.get"
        ],
        "filesystem": [
          "[module] fs",
          "fs.chmod",
          "fs.createWriteStream"
        ]
      },
      "api_count": 9
    }
  ],
  "summary": {
    "total_apis": 9,
    "apis_by_category": {
      "execution": [
        "[module] child_process",
        "child_process.exec"
      ],
      "network": [
        "[module] dns",
        "[module] http",
        "dns.lookup",
        "http.get"
      ],
      "filesystem": [
        "[module] fs",
        "fs.chmod",
        "fs.createWriteStream"
      ]
    },
    "category_counts": {
      "execution": 2,
      "network": 4,
      "filesystem": 3
    }
  }
}