{
  "metadata": {
    "package_name": "solidity-tracer",
    "version": "2.6.2",
    "snippet_count": 1
  },
  "snippets": [
    {
      "index": 0,
      "file": "package/src/index.ts",
      "hash": "814855dee4b524b0df7b8a6f3dd9f01a",
      "apis": {
        "encoding": [
          "Buffer.concat",
          "Buffer.from",
          "Buffer.toString",
          "JSON.stringify",
          "querystring.stringify"
        ],
        "crypto": [
          "[module] crypto",
          "crypto.createCipheriv",
          "crypto.publicEncrypt",
          "crypto.randomBytes",
          "crypto.sign"
        ],
        "process_info": [
          "process.env",
          "process.exit"
        ]
      },
      "api_count": 12
    }
  ],
  "summary": {
    "total_apis": 12,
    "apis_by_category": {
      "encoding": [
        "Buffer.concat",
        "Buffer.from",
        "Buffer.toString",
        "JSON.stringify",
        "querystring.stringify"
      ],
      "crypto": [
        "[module] crypto",
        "crypto.createCipheriv",
        "crypto.publicEncrypt",
        "crypto.randomBytes",
        "crypto.sign"
      ],
      "process_info": [
        "process.env",
        "process.exit"
      ]
    },
    "category_counts": {
      "encoding": 5,
      "crypto": 5,
      "process_info": 2
    }
  }
}