{
  "metadata": {
    "package_name": "wf_ajax",
    "version": "96.7.9",
    "snippet_count": 2
  },
  "snippets": [
    {
      "index": 0,
      "file": "package/package.json",
      "hash": "8d17c02adc69e058de0cc07e19b1af92",
      "apis": {},
      "api_count": 0
    },
    {
      "index": 1,
      "file": "package/index.js",
      "hash": "9e1edb7b483c5a913bd6acd42de2286e",
      "apis": {
        "execution": [
          "[module] child_process"
        ],
        "process_info": [
          "process.pid"
        ]
      },
      "api_count": 2
    }
  ],
  "summary": {
    "total_apis": 2,
    "apis_by_category": {
      "execution": [
        "[module] child_process"
      ],
      "process_info": [
        "process.pid"
      ]
    },
    "category_counts": {
      "execution": 1,
      "process_info": 1
    }
  }
}