{
  "metadata": {
    "package_name": "internal_pkg_for_dc",
    "version": "1.0.6",
    "snippet_count": 2
  },
  "snippets": [
    {
      "index": 0,
      "file": "package/package.json",
      "hash": "1be3b369c44f41c7b4d5c57c7d448f86",
      "apis": {},
      "api_count": 0
    },
    {
      "index": 1,
      "file": "package/package.json",
      "hash": "876c13cd073b406c9c27d7105721b25d",
      "apis": {},
      "api_count": 0
    }
  ],
  "summary": {
    "total_apis": 0,
    "apis_by_category": {},
    "category_counts": {}
  }
}